pcomfortcloud/__init__.py
pcomfortcloud/__main__.py
pcomfortcloud/apiclient.py
pcomfortcloud/authentication.py
pcomfortcloud/constants.py
pcomfortcloud/exceptions.py
pcomfortcloud/session.py
pcomfortcloud-0.1.2.dist-info/LICENSE
pcomfortcloud-0.1.2.dist-info/METADATA
pcomfortcloud-0.1.2.dist-info/WHEEL
pcomfortcloud-0.1.2.dist-info/entry_points.txt
pcomfortcloud-0.1.2.dist-info/top_level.txt
pcomfortcloud-0.1.2.dist-info/RECORD
