Metadata-Version: 2.1
Name: pcomfortcloud
Version: 0.1.2
Summary: Read and change status of Panasonic Comfort Cloud devices
Home-page: http://github.com/lostfields/python-panasonic-comfort-cloud
Author: Lostfields
License: MIT
Keywords: home automation panasonic climate
Classifier: Topic :: Home Automation
Classifier: License :: OSI Approved :: MIT License
Classifier: Programming Language :: Python :: 3.4
Classifier: Programming Language :: Python :: 3.5
License-File: LICENSE
Requires-Dist: requests >=2.20.0
